examples/mlx90632_dump.py
examples/mlx90632_hello_world.py
mlx90632/MemFile.py
mlx90632/hw_ftdi_2232h.py
mlx90632/hw_i2c_hal.py
mlx90632/hw_rpi_gpio_bitbang.py
mlx90632/hw_rpi_gpio_i2chw.py
mlx90632/hw_usb_evb90632.py
mlx90632/mlx90632.py
mlx90632/pympt/PyWinUsbChannel.py
mlx90632/pympt/UsbHidChannel.py
mlx90632/pympt/__init__.py
mlx90632/pympt/channel.py
mlx90632/pympt/core.py
mlx90632_driver-1.3.0.dist-info/LICENSE
mlx90632_driver-1.3.0.dist-info/METADATA
mlx90632_driver-1.3.0.dist-info/NOTICE
mlx90632_driver-1.3.0.dist-info/WHEEL
mlx90632_driver-1.3.0.dist-info/entry_points.txt
mlx90632_driver-1.3.0.dist-info/top_level.txt
mlx90632_driver-1.3.0.dist-info/RECORD
