Metadata-Version: 2.1
Name: mlx90632-driver
Version: 1.3.0
Summary: Python library for MLX90632
Home-page: https://github.com/melexis-fir/mlx90632-driver-py
License: Apache License, Version 2.0
Download-URL: https://github.com/melexis-fir/mlx90632-driver-py/archive/V1.3.0.tar.gz
Platform: UNKNOWN
Classifier: Development Status :: 5 - Production/Stable
Classifier: Intended Audience :: Developers
Classifier: License :: OSI Approved :: Apache Software License
Classifier: Operating System :: Microsoft :: Windows
Classifier: Operating System :: POSIX
Classifier: Programming Language :: Python
Classifier: Programming Language :: Python :: 3
Classifier: Programming Language :: Python :: 3.4
Classifier: Programming Language :: Python :: 3.5
Classifier: Programming Language :: Python :: 3.6
Classifier: Programming Language :: Python :: 3.7
Classifier: Programming Language :: Python :: 3.8
Classifier: Topic :: Utilities
Requires-Dist: bincopy (>=17.8.0)
Requires-Dist: pyftdi (>=0.51.2)
Requires-Dist: ctypes-callable (>=1.0.0)
Requires-Dist: Jetson.GPIO (>=2.0.8) ; platform_machine == "aarch64"
Requires-Dist: smbus2 (>=0.3.0) ; platform_machine == "aarch64"
Requires-Dist: RPi.GPIO (>=0.7.0) ; platform_machine == "armv7l"
Requires-Dist: smbus2 (>=0.3.0) ; platform_machine == "armv7l"
Requires-Dist: hid (>=1.0.4) ; platform_system == "Linux"
Requires-Dist: pywinusb (>=0.4.2) ; platform_system == "Windows"
